mlpm/__init__.py
mlpm/app.py
mlpm/handler.py
mlpm/response.py
mlpm/schemas.py
mlpm/server.py
mlpm/solver.py
mlpm/utility.py
mlpm-1.4.1.1.dist-info/METADATA
mlpm-1.4.1.1.dist-info/WHEEL
mlpm-1.4.1.1.dist-info/top_level.txt
mlpm-1.4.1.1.dist-info/RECORD
