Metadata-Version: 2.1
Name: mlpm
Version: 1.4.1.1
Summary: Machine Learning Package Manager
Home-page: https://aid.autoai.org
Author: Xiaozhe Yao
Author-email: askxzyao@gmail.com
License: MIT
Project-URL: Bug Tracker, https://github.com/autoai-org/aid/issues
Project-URL: Documentation, https://aid.autoai.org
Project-URL: Source Code, https://github.com/autoai-org/aid
Platform: UNKNOWN
Classifier: Programming Language :: Python :: 3
Classifier: License :: OSI Approved :: MIT License
Classifier: Operating System :: OS Independent
Classifier: Intended Audience :: Developers
Classifier: Intended Audience :: Education
Classifier: Intended Audience :: Information Technology
Classifier: Intended Audience :: Science/Research
Classifier: Topic :: Scientific/Engineering
Classifier: Topic :: Scientific/Engineering :: Image Recognition
Classifier: Topic :: Software Development
Requires-Dist: gunicorn
Requires-Dist: uvicorn
Requires-Dist: quart
Requires-Dist: toml
Requires-Dist: requests
Requires-Dist: numpy
Requires-Dist: werkzeug
Requires-Dist: quart-openapi
